ai_trust_score/__init__.py
ai_trust_score/client.py
ai_trust_score-1.0.7.dist-info/METADATA
ai_trust_score-1.0.7.dist-info/WHEEL
ai_trust_score-1.0.7.dist-info/top_level.txt
ai_trust_score-1.0.7.dist-info/RECORD
