Metadata-Version: 2.4
Name: ai-trust-score
Version: 1.0.7
Summary: A Python client for accessing the Tumeryk AI Trust Score API
Home-page: https://tumeryk.com
Author: Tumeryk
Author-email: support@tumeryk.com
Classifier: Programming Language :: Python :: 3
Classifier: License :: OSI Approved :: MIT License
Classifier: Operating System :: OS Independent
Requires-Python: >=3.7
Requires-Dist: requests>=2.31.0
Dynamic: author
Dynamic: author-email
Dynamic: classifier
Dynamic: description
Dynamic: description-content-type
Dynamic: home-page
Dynamic: requires-dist
Dynamic: requires-python
Dynamic: summary
